spongemock/__init__.py
spongemock/__main__.py
spongemock/spongemock.py
spongemock-1.0.0.data/data/LICENSE
spongemock-1.0.0.data/data/README.rst
spongemock-1.0.0.dist-info/LICENSE
spongemock-1.0.0.dist-info/METADATA
spongemock-1.0.0.dist-info/WHEEL
spongemock-1.0.0.dist-info/entry_points.txt
spongemock-1.0.0.dist-info/pbr.json
spongemock-1.0.0.dist-info/top_level.txt
spongemock-1.0.0.dist-info/zip-safe
spongemock-1.0.0.dist-info/RECORD
