Metadata-Version: 2.1
Name: spongemock
Version: 1.0.0
Summary: Mock some text like spongebob would. mOCk SoMe TexT lIKe SpONGebOb wOuLd.
Home-page: https://github.com/nkrim/spongemock
Author: Noah Krim
Author-email: nkrim62@gmail.com
License: MIT License
Keywords: spongemock spongebob squarepants meme mock text random
Classifier: Development Status :: 5 - Production/Stable
Classifier: Environment :: Console
Classifier: Intended Audience :: End Users/Desktop
Classifier: License :: OSI Approved :: MIT License
Classifier: Natural Language :: English
Classifier: Operating System :: OS Independent
Classifier: Programming Language :: Python
Classifier: Programming Language :: Python :: 2
Classifier: Programming Language :: Python :: 3
Classifier: Topic :: Text Processing
Classifier: Topic :: Text Processing :: Filters
Classifier: Topic :: Text Processing :: General
Classifier: Topic :: Utilities
License-File: LICENSE
